README.rst
setup.py
django_chart_js/__init__.py
django_chart_js/models.py
django_chart_js.egg-info/PKG-INFO
django_chart_js.egg-info/SOURCES.txt
django_chart_js.egg-info/dependency_links.txt
django_chart_js.egg-info/top_level.txt
django_chart_js/templatetags/__init__.py
django_chart_js/templatetags/chart_js_tags.py