Metadata-Version: 1.1
Name: django-chart-js
Version: 0.0.3
Summary: Django Chart.js wrapper
Home-page: UNKNOWN
Author: deliro
Author-email: t4k.kitaetz@gmail.com
License: Apache 2.0
Platform: UNKNOWN
Classifier: Development Status :: 4 - Beta
Classifier: Intended Audience :: Developers
Classifier: Natural Language :: English
Classifier: License :: OSI Approved :: Apache Software License
Classifier: Programming Language :: Python
Classifier: Programming Language :: Python :: 3
Classifier: Programming Language :: Python :: 3.3
Classifier: Programming Language :: Python :: 3.4
Requires: django
